{
  "$schema": "https://mintlify.com/schema.json",
  "name": "ActiveProspect Account Documentation",
  "logo": {
    "dark": "/logo/ap-full-black-blue.png",
    "light": "/logo/ap-full-black-blue.png"
  },
  "favicon": "/favicon.svg",
  "colors": {
    "primary": "#3fb1f2",
    "light": "#07C983",
    "dark": "#2ecc71",
    "anchors": {
      "from": "#3fb1f2",
      "to": "#3fb1f2"
    }
  },
  "topbarCtaButton": {
    "name": "SSO App",
    "url": "https://account.activeprospect.com"
  },
  "anchors": [
    {
      "name": "Documentation",
      "icon": "book-open-cover",
      "url": "/"
    },
    {
      "name": "API Reference",
      "url": "/api-reference/introduction",
      "icon": "square-terminal"
    }
  ],
  "navigation": [
    {
      "group": "Get Started",
      "pages": [
        "introduction"
      ]
    },
    {
      "group": "Guides",
      "pages": [
        "guides/invite-to-connect"
      ]
    },
    {
      "group": "API Reference",
      "pages": [
        "api-reference/introduction",
        "api-reference/kafka",
        {
          "group": "Accounts",
          "pages": [
            {
              "group": "Network API",
              "pages": [
                "api-reference/network/introduction",
                {
                  "group": "Account",
                  "pages": [
                    "api-reference/network/account/object",
                    "api-reference/network/account/get-account",
                    "api-reference/network/account/update-account"
                  ]
                },
                {
                  "group": "Company",
                  "pages": [
                    "api-reference/network/company/object",
                    "api-reference/network/company/get-company",
                    "api-reference/network/company/update-company"
                  ]
                },
                {
                  "group": "Connections",
                  "pages": [
                    "api-reference/network/connections/list-connections-of-a-company",
                    "api-reference/network/connections/get-a-connection"
                  ]
                },
                {
                  "group": "Invitations",
                  "pages": [
                    "api-reference/network/invitations/list-received-invitations",
                    "api-reference/network/invitations/send-an-invitation-to-connect",
                    "api-reference/network/invitations/get-an-invitation-using-invite-code"
                  ]
                },
                {
                  "group": "Errors",
                  "pages": [
                    "api-reference/errors/overview",
                    "api-reference/errors/unauthorized",
                    "api-reference/errors/notfound",
                    "api-reference/errors/internalservererror",
                    "api-reference/errors/bad-request",
                    "api-reference/errors/unprocessablecontent"
                  ]
                }
              ]
            }
          ]
        },
        {
          "group": "TrustedForm",
          "pages": [
            "api-reference/trustedform/introduction",
            {
              "group": "Certificate URL",
              "pages": [
                "api-reference/trustedform/certificate-url/run-certificate-operations"
              ]
            }
          ]
        },
        {
          "group": "LeadConduit",
          "pages": [
            "api-reference/leadconduit/introduction"
          ]
        },
        {
          "group": "Leadsbridge",
          "pages": [
            "api-reference/leadsbridge/introduction"
          ]
        }
      ]
    }
  ],
  "footerSocials": {
    "github": "https://github.com/activeprospect/sso"
  }
}
